{
    "balance": 7716.300000000001,
    "initial_balance": 10000.0,
    "bets": [
        {
            "id": "POR@TOR",
            "game": "Trail Blazers vs Raptors",
            "sport": "other",
            "timestamp": "2025-12-03T01:24:50.305699",
            "legs": [
                {
                    "platform": "Kalshi",
                    "price": 18,
                    "eff": 19.349999999999998,
                    "team": "Trail Blazers",
                    "code": "POR",
                    "market_id": null,
                    "url": "https://kalshi.com/markets/KXNBAGAME-25DEC02PORTOR-POR",
                    "fee_rate": 0.07,
                    "cost_usd": 19.349999999999998,
                    "fee_usd": 1.3499999999999976,
                    "payout_usd": 100.0,
                    "slippage_usd": 0.09
                },
                {
                    "platform": "Polymarket",
                    "price": 60.5,
                    "eff": 62.012499999999996,
                    "team": "Raptors",
                    "code": "TOR",
                    "market_id": "705401",
                    "url": "https://polymarket.com/event/nba-por-tor-2025-12-02",
                    "fee_rate": 0.02,
                    "cost_usd": 62.0125,
                    "fee_usd": 1.5125,
                    "payout_usd": 100.0,
                    "slippage_usd": 0.3025
                }
            ],
            "quantity": 100.0,
            "cost": 81.3625,
            "payout": 100.0,
            "profit": 18.637500000000003,
            "roi_percent": 22.90674450760486,
            "status": "pending",
            "settled_amount": 0.0,
            "realized_profit": 0.0,
            "fees_total_usd": 2.8624999999999976,
            "slippage_total_usd": 0.39249999999999996,
            "arb_type": "perfect",
            "total_cost_per_unit": 81.3625,
            "bet_amount_config": 100.0
        },
        {
            "id": "Predators@Avalanche",
            "game": "Predators vs Avalanche",
            "sport": "other",
            "timestamp": "2025-12-03T01:24:50.308452",
            "legs": [
                {
                    "platform": "Kalshi",
                    "price": 26,
                    "eff": 27.95,
                    "team": "Predators",
                    "code": "Predators",
                    "market_id": null,
                    "url": "https://kalshi.com/markets/KXNBAGAME-25DEC03PORCLE-POR",
                    "fee_rate": 0.07,
                    "cost_usd": 27.95,
                    "fee_usd": 1.95,
                    "payout_usd": 100.0,
                    "slippage_usd": 0.13
                },
                {
                    "platform": "Polymarket",
                    "price": 50.5,
                    "eff": 51.762499999999996,
                    "team": "Avalanche",
                    "code": "Avalanche",
                    "market_id": "685748",
                    "url": "https://polymarket.com/event/nhl-nsh-col-2025-12-14",
                    "fee_rate": 0.02,
                    "cost_usd": 51.7625,
                    "fee_usd": 1.2625,
                    "payout_usd": 100.0,
                    "slippage_usd": 0.2525
                }
            ],
            "quantity": 100.0,
            "cost": 79.71249999999999,
            "payout": 100.0,
            "profit": 20.28750000000001,
            "roi_percent": 25.450838952485512,
            "status": "pending",
            "settled_amount": 0.0,
            "realized_profit": 0.0,
            "fees_total_usd": 3.2125,
            "slippage_total_usd": 0.3825,
            "arb_type": "perfect",
            "total_cost_per_unit": 79.71249999999999,
            "bet_amount_config": 100.0
        },
        {
            "id": "MIN@NOP",
            "game": "Timberwolves vs Pelicans",
            "sport": "other",
            "timestamp": "2025-12-03T02:06:49.639379",
            "legs": [
                {
                    "platform": "Kalshi",
                    "price": 56,
                    "eff": 60.199999999999996,
                    "team": "Timberwolves",
                    "code": "MIN",
                    "market_id": null,
                    "url": "https://kalshi.com/markets/KXNBAGAME-25DEC02MINNOP-MIN",
                    "fee_rate": 0.07,
                    "cost_usd": 60.2,
                    "fee_usd": 4.2,
                    "payout_usd": 100.0,
                    "slippage_usd": 0.28
                },
                {
                    "platform": "Polymarket",
                    "price": 23.5,
                    "eff": 24.0875,
                    "team": "Pelicans",
                    "code": "NOP",
                    "market_id": "705407",
                    "url": "https://polymarket.com/event/nba-min-nop-2025-12-02",
                    "fee_rate": 0.02,
                    "cost_usd": 24.0875,
                    "fee_usd": 0.5875,
                    "payout_usd": 100.0,
                    "slippage_usd": 0.1175
                }
            ],
            "quantity": 100.0,
            "cost": 84.2875,
            "payout": 100.0,
            "profit": 15.712500000000007,
            "roi_percent": 18.641554204360087,
            "status": "pending",
            "settled_amount": 0.0,
            "realized_profit": 0.0,
            "fees_total_usd": 4.7875000000000005,
            "slippage_total_usd": 0.3975,
            "arb_type": "perfect",
            "total_cost_per_unit": 84.2875,
            "bet_amount_config": 100.0
        },
        {
            "id": "MEM@SAS",
            "game": "Grizzlies vs Spurs",
            "sport": "other",
            "timestamp": "2025-12-03T02:09:23.103103",
            "legs": [
                {
                    "platform": "Kalshi",
                    "price": 27,
                    "eff": 29.025,
                    "team": "Grizzlies",
                    "code": "MEM",
                    "market_id": null,
                    "url": "https://kalshi.com/markets/KXNBAGAME-25DEC02MEMSAS-MEM",
                    "fee_rate": 0.07,
                    "cost_usd": 29.025,
                    "fee_usd": 2.025,
                    "payout_usd": 100.0,
                    "slippage_usd": 0.135
                },
                {
                    "platform": "Polymarket",
                    "price": 64.0,
                    "eff": 65.6,
                    "team": "Spurs",
                    "code": "SAS",
                    "market_id": "705409",
                    "url": "https://polymarket.com/event/nba-mem-sas-2025-12-02",
                    "fee_rate": 0.02,
                    "cost_usd": 65.6,
                    "fee_usd": 1.599999999999991,
                    "payout_usd": 100.0,
                    "slippage_usd": 0.32
                }
            ],
            "quantity": 100.0,
            "cost": 94.625,
            "payout": 100.0,
            "profit": 5.375,
            "roi_percent": 5.680317040951123,
            "status": "pending",
            "settled_amount": 0.0,
            "realized_profit": 0.0,
            "fees_total_usd": 3.624999999999991,
            "slippage_total_usd": 0.455,
            "arb_type": "perfect",
            "total_cost_per_unit": 94.625,
            "bet_amount_config": 100.0
        },
        {
            "id": "NYK@BOS",
            "game": "Knicks vs Celtics",
            "sport": "other",
            "timestamp": "2025-12-03T02:09:49.127532",
            "legs": [
                {
                    "platform": "Kalshi",
                    "price": 44,
                    "eff": 47.3,
                    "team": "Knicks",
                    "code": "NYK",
                    "market_id": null,
                    "url": "https://kalshi.com/markets/KXNBAGAME-25DEC02NYKBOS-NYK",
                    "fee_rate": 0.07,
                    "cost_usd": 47.3,
                    "fee_usd": 3.3,
                    "payout_usd": 100.0,
                    "slippage_usd": 0.22
                },
                {
                    "platform": "Polymarket",
                    "price": 43.5,
                    "eff": 44.5875,
                    "team": "Celtics",
                    "code": "BOS",
                    "market_id": "705404",
                    "url": "https://polymarket.com/event/nba-nyk-bos-2025-12-02",
                    "fee_rate": 0.02,
                    "cost_usd": 44.5875,
                    "fee_usd": 1.0875,
                    "payout_usd": 100.0,
                    "slippage_usd": 0.2175
                }
            ],
            "quantity": 100.0,
            "cost": 91.88749999999999,
            "payout": 100.0,
            "profit": 8.112500000000011,
            "roi_percent": 8.828730784927235,
            "status": "pending",
            "settled_amount": 0.0,
            "realized_profit": 0.0,
            "fees_total_usd": 4.387499999999999,
            "slippage_total_usd": 0.4375,
            "arb_type": "perfect",
            "total_cost_per_unit": 91.88749999999999,
            "bet_amount_config": 100.0
        },
        {
            "id": "DET@CBJ",
            "game": "Red Wings vs Blue Jackets",
            "sport": "NHL",
            "timestamp": "2025-12-03T12:19:23.507740",
            "legs": [
                {
                    "platform": "Kalshi",
                    "price": 31.5,
                    "eff": 33.8625,
                    "team": "Red Wings",
                    "code": "DET",
                    "market_id": null,
                    "url": "https://kalshi.com/markets/KXNHLGAME-25DEC04DETCBJ-DET",
                    "fee_rate": 0.07,
                    "cost_usd": 33.8625,
                    "fee_usd": 2.3624999999999954,
                    "payout_usd": 100.0,
                    "slippage_usd": 0.1575
                },
                {
                    "platform": "Kalshi",
                    "price": 31.5,
                    "eff": 33.8625,
                    "team": "Blue Jackets",
                    "code": "CBJ",
                    "market_id": null,
                    "url": "https://kalshi.com/markets/KXNHLGAME-25DEC04DETCBJ-DET",
                    "fee_rate": 0.07,
                    "cost_usd": 33.8625,
                    "fee_usd": 2.3624999999999954,
                    "payout_usd": 100.0,
                    "slippage_usd": 0.1575
                }
            ],
            "quantity": 100.0,
            "cost": 67.725,
            "payout": 100.0,
            "profit": 32.275,
            "roi_percent": 47.656,
            "status": "pending",
            "settled_amount": 0.0,
            "realized_profit": 0.0,
            "fees_total_usd": 4.724999999999991,
            "slippage_total_usd": 0.315,
            "arb_type": "perfect",
            "total_cost_per_unit": 67.725,
            "bet_amount_config": 100.0
        },
        {
            "id": "CHE@EVE",
            "game": "Chelsea vs Everton",
            "sport": "SOCCER",
            "timestamp": "2025-12-03T12:19:23.509515",
            "legs": [
                {
                    "platform": "Kalshi",
                    "price": 45.0,
                    "eff": 48.375,
                    "team": "Chelsea",
                    "code": "CHE",
                    "market_id": null,
                    "url": "https://kalshi.com/markets/KXEPLGAME-25DEC13CFCEVE-TIE",
                    "fee_rate": 0.07,
                    "cost_usd": 48.375,
                    "fee_usd": 3.375,
                    "payout_usd": 100.0,
                    "slippage_usd": 0.225
                },
                {
                    "platform": "Polymarket",
                    "price": 21.0,
                    "eff": 21.525,
                    "team": "Everton",
                    "code": "EVE",
                    "market_id": "768241",
                    "url": "https://polymarket.com/event/epl-che-eve-2025-12-13",
                    "fee_rate": 0.02,
                    "cost_usd": 21.525,
                    "fee_usd": 0.525,
                    "payout_usd": 100.0,
                    "slippage_usd": 0.105
                }
            ],
            "quantity": 100.0,
            "cost": 69.9,
            "payout": 100.0,
            "profit": 30.099999999999998,
            "roi_percent": 43.0615,
            "status": "pending",
            "settled_amount": 0.0,
            "realized_profit": 0.0,
            "fees_total_usd": 3.9,
            "slippage_total_usd": 0.33,
            "arb_type": "perfect",
            "total_cost_per_unit": 69.9,
            "bet_amount_config": 100.0
        },
        {
            "id": "UTA@VAN",
            "game": "Utah vs Canucks",
            "sport": "NHL",
            "timestamp": "2025-12-03T12:19:23.510735",
            "legs": [
                {
                    "platform": "Kalshi",
                    "price": 34.5,
                    "eff": 37.0875,
                    "team": "Utah",
                    "code": "UTA",
                    "market_id": null,
                    "url": "https://kalshi.com/markets/KXNHLGAME-25DEC05UTAVAN-VAN",
                    "fee_rate": 0.07,
                    "cost_usd": 37.0875,
                    "fee_usd": 2.5875,
                    "payout_usd": 100.0,
                    "slippage_usd": 0.1725
                },
                {
                    "platform": "Kalshi",
                    "price": 31.5,
                    "eff": 33.8625,
                    "team": "Canucks",
                    "code": "VAN",
                    "market_id": null,
                    "url": "https://kalshi.com/markets/KXNHLGAME-25DEC05UTAVAN-VAN",
                    "fee_rate": 0.07,
                    "cost_usd": 33.8625,
                    "fee_usd": 2.3624999999999954,
                    "payout_usd": 100.0,
                    "slippage_usd": 0.1575
                }
            ],
            "quantity": 100.0,
            "cost": 70.95,
            "payout": 100.0,
            "profit": 29.049999999999997,
            "roi_percent": 40.9443,
            "status": "pending",
            "settled_amount": 0.0,
            "realized_profit": 0.0,
            "fees_total_usd": 4.949999999999996,
            "slippage_total_usd": 0.32999999999999996,
            "arb_type": "perfect",
            "total_cost_per_unit": 70.95,
            "bet_amount_config": 100.0
        },
        {
            "id": "BUF@WPG",
            "game": "Sabres vs Jets",
            "sport": "NHL",
            "timestamp": "2025-12-03T12:19:23.512210",
            "legs": [
                {
                    "platform": "Kalshi",
                    "price": 29.0,
                    "eff": 31.175,
                    "team": "Sabres",
                    "code": "BUF",
                    "market_id": null,
                    "url": "https://kalshi.com/markets/KXNHLGAME-25DEC05BUFWPG-WPG",
                    "fee_rate": 0.07,
                    "cost_usd": 31.175,
                    "fee_usd": 2.175,
                    "payout_usd": 100.0,
                    "slippage_usd": 0.145
                },
                {
                    "platform": "Kalshi",
                    "price": 37.5,
                    "eff": 40.3125,
                    "team": "Jets",
                    "code": "WPG",
                    "market_id": null,
                    "url": "https://kalshi.com/markets/KXNHLGAME-25DEC05BUFWPG-WPG",
                    "fee_rate": 0.07,
                    "cost_usd": 40.3125,
                    "fee_usd": 2.8125,
                    "payout_usd": 100.0,
                    "slippage_usd": 0.1875
                }
            ],
            "quantity": 100.0,
            "cost": 71.4875,
            "payout": 100.0,
            "profit": 28.512500000000003,
            "roi_percent": 39.8846,
            "status": "pending",
            "settled_amount": 0.0,
            "realized_profit": 0.0,
            "fees_total_usd": 4.9875,
            "slippage_total_usd": 0.3325,
            "arb_type": "perfect",
            "total_cost_per_unit": 71.4875,
            "bet_amount_config": 100.0
        },
        {
            "id": "WSH@ANA",
            "game": "Capitals vs Ducks",
            "sport": "NHL",
            "timestamp": "2025-12-03T12:19:23.513867",
            "legs": [
                {
                    "platform": "Kalshi",
                    "price": 36.0,
                    "eff": 38.7,
                    "team": "Capitals",
                    "code": "WSH",
                    "market_id": null,
                    "url": "https://kalshi.com/markets/KXNHLGAME-25DEC05WSHANA-WSH",
                    "fee_rate": 0.07,
                    "cost_usd": 38.7,
                    "fee_usd": 2.7000000000000046,
                    "payout_usd": 100.0,
                    "slippage_usd": 0.18
                },
                {
                    "platform": "Kalshi",
                    "price": 31.0,
                    "eff": 33.325,
                    "team": "Ducks",
                    "code": "ANA",
                    "market_id": null,
                    "url": "https://kalshi.com/markets/KXNHLGAME-25DEC05WSHANA-WSH",
                    "fee_rate": 0.07,
                    "cost_usd": 33.325,
                    "fee_usd": 2.3250000000000046,
                    "payout_usd": 100.0,
                    "slippage_usd": 0.155
                }
            ],
            "quantity": 100.0,
            "cost": 72.025,
            "payout": 100.0,
            "profit": 27.975,
            "roi_percent": 38.8407,
            "status": "pending",
            "settled_amount": 0.0,
            "realized_profit": 0.0,
            "fees_total_usd": 5.025000000000009,
            "slippage_total_usd": 0.33499999999999996,
            "arb_type": "perfect",
            "total_cost_per_unit": 72.025,
            "bet_amount_config": 100.0
        },
        {
            "id": "EVE@NFO",
            "game": "Everton vs Nottingham Forest",
            "sport": "SOCCER",
            "timestamp": "2025-12-03T12:19:23.515850",
            "legs": [
                {
                    "platform": "Kalshi",
                    "price": 44.5,
                    "eff": 47.8375,
                    "team": "Everton",
                    "code": "EVE",
                    "market_id": null,
                    "url": "https://kalshi.com/markets/KXEPLGAME-25DEC06EVENFO-TIE",
                    "fee_rate": 0.07,
                    "cost_usd": 47.8375,
                    "fee_usd": 3.3375,
                    "payout_usd": 100.0,
                    "slippage_usd": 0.2225
                },
                {
                    "platform": "Kalshi",
                    "price": 25.5,
                    "eff": 27.4125,
                    "team": "Nottingham Forest",
                    "code": "NFO",
                    "market_id": null,
                    "url": "https://kalshi.com/markets/KXEPLGAME-25DEC06EVENFO-TIE",
                    "fee_rate": 0.07,
                    "cost_usd": 27.4125,
                    "fee_usd": 1.9125,
                    "payout_usd": 100.0,
                    "slippage_usd": 0.1275
                }
            ],
            "quantity": 100.0,
            "cost": 75.25,
            "payout": 100.0,
            "profit": 24.75,
            "roi_percent": 32.8904,
            "status": "pending",
            "settled_amount": 0.0,
            "realized_profit": 0.0,
            "fees_total_usd": 5.25,
            "slippage_total_usd": 0.35,
            "arb_type": "perfect",
            "total_cost_per_unit": 75.25,
            "bet_amount_config": 100.0
        },
        {
            "id": "WOL@NFO",
            "game": "Wolves vs Nottingham Forest",
            "sport": "SOCCER",
            "timestamp": "2025-12-03T12:19:23.518840",
            "legs": [
                {
                    "platform": "Kalshi",
                    "price": 29.5,
                    "eff": 31.7125,
                    "team": "Wolves",
                    "code": "WOL",
                    "market_id": null,
                    "url": "https://kalshi.com/markets/KXEPLGAME-25DEC03WOLNFO-WOL",
                    "fee_rate": 0.07,
                    "cost_usd": 31.7125,
                    "fee_usd": 2.2125,
                    "payout_usd": 100.0,
                    "slippage_usd": 0.1475
                },
                {
                    "platform": "Kalshi",
                    "price": 42.0,
                    "eff": 45.15,
                    "team": "Nottingham Forest",
                    "code": "NFO",
                    "market_id": null,
                    "url": "https://kalshi.com/markets/KXEPLGAME-25DEC03WOLNFO-WOL",
                    "fee_rate": 0.07,
                    "cost_usd": 45.15,
                    "fee_usd": 3.15,
                    "payout_usd": 100.0,
                    "slippage_usd": 0.21
                }
            ],
            "quantity": 100.0,
            "cost": 76.8625,
            "payout": 100.0,
            "profit": 23.1375,
            "roi_percent": 30.1025,
            "status": "pending",
            "settled_amount": 0.0,
            "realized_profit": 0.0,
            "fees_total_usd": 5.3625,
            "slippage_total_usd": 0.3575,
            "arb_type": "perfect",
            "total_cost_per_unit": 76.8625,
            "bet_amount_config": 100.0
        },
        {
            "id": "FUL@CRY",
            "game": "Fulham vs Crystal Palace",
            "sport": "SOCCER",
            "timestamp": "2025-12-03T12:19:23.520979",
            "legs": [
                {
                    "platform": "Kalshi",
                    "price": 36.5,
                    "eff": 39.2375,
                    "team": "Fulham",
                    "code": "FUL",
                    "market_id": null,
                    "url": "https://kalshi.com/markets/KXEPLGAME-25DEC07FULCRY-TIE",
                    "fee_rate": 0.07,
                    "cost_usd": 39.2375,
                    "fee_usd": 2.7374999999999954,
                    "payout_usd": 100.0,
                    "slippage_usd": 0.1825
                },
                {
                    "platform": "Kalshi",
                    "price": 35.5,
                    "eff": 38.1625,
                    "team": "Crystal Palace",
                    "code": "CRY",
                    "market_id": null,
                    "url": "https://kalshi.com/markets/KXEPLGAME-25DEC07FULCRY-TIE",
                    "fee_rate": 0.07,
                    "cost_usd": 38.1625,
                    "fee_usd": 2.6625,
                    "payout_usd": 100.0,
                    "slippage_usd": 0.1775
                }
            ],
            "quantity": 100.0,
            "cost": 77.4,
            "payout": 100.0,
            "profit": 22.6,
            "roi_percent": 29.199,
            "status": "pending",
            "settled_amount": 0.0,
            "realized_profit": 0.0,
            "fees_total_usd": 5.399999999999995,
            "slippage_total_usd": 0.36,
            "arb_type": "perfect",
            "total_cost_per_unit": 77.4,
            "bet_amount_config": 100.0
        },
        {
            "id": "STL@BOS",
            "game": "Blues vs Bruins",
            "sport": "NHL",
            "timestamp": "2025-12-03T12:19:23.522595",
            "legs": [
                {
                    "platform": "Kalshi",
                    "price": 32.5,
                    "eff": 34.9375,
                    "team": "Blues",
                    "code": "STL",
                    "market_id": null,
                    "url": "https://kalshi.com/markets/KXNHLGAME-25DEC04STLBOS-STL",
                    "fee_rate": 0.07,
                    "cost_usd": 34.9375,
                    "fee_usd": 2.4375,
                    "payout_usd": 100.0,
                    "slippage_usd": 0.1625
                },
                {
                    "platform": "Kalshi",
                    "price": 40.5,
                    "eff": 43.5375,
                    "team": "Bruins",
                    "code": "BOS",
                    "market_id": null,
                    "url": "https://kalshi.com/markets/KXNHLGAME-25DEC04STLBOS-STL",
                    "fee_rate": 0.07,
                    "cost_usd": 43.5375,
                    "fee_usd": 3.0375,
                    "payout_usd": 100.0,
                    "slippage_usd": 0.2025
                }
            ],
            "quantity": 100.0,
            "cost": 78.475,
            "payout": 100.0,
            "profit": 21.525,
            "roi_percent": 27.4291,
            "status": "pending",
            "settled_amount": 0.0,
            "realized_profit": 0.0,
            "fees_total_usd": 5.475,
            "slippage_total_usd": 0.365,
            "arb_type": "perfect",
            "total_cost_per_unit": 78.475,
            "bet_amount_config": 100.0
        },
        {
            "id": "AVL@ARS",
            "game": "Aston Villa vs Arsenal",
            "sport": "SOCCER",
            "timestamp": "2025-12-03T12:19:23.524209",
            "legs": [
                {
                    "platform": "Kalshi",
                    "price": 21.5,
                    "eff": 23.1125,
                    "team": "Aston Villa",
                    "code": "AVL",
                    "market_id": null,
                    "url": "https://kalshi.com/markets/KXEPLGAME-25DEC06AVLARS-TIE",
                    "fee_rate": 0.07,
                    "cost_usd": 23.1125,
                    "fee_usd": 1.6125,
                    "payout_usd": 100.0,
                    "slippage_usd": 0.1075
                },
                {
                    "platform": "Kalshi",
                    "price": 52.5,
                    "eff": 56.4375,
                    "team": "Arsenal",
                    "code": "ARS",
                    "market_id": null,
                    "url": "https://kalshi.com/markets/KXEPLGAME-25DEC06AVLARS-TIE",
                    "fee_rate": 0.07,
                    "cost_usd": 56.4375,
                    "fee_usd": 3.9375,
                    "payout_usd": 100.0,
                    "slippage_usd": 0.2625
                }
            ],
            "quantity": 100.0,
            "cost": 79.55,
            "payout": 100.0,
            "profit": 20.45,
            "roi_percent": 25.7071,
            "status": "pending",
            "settled_amount": 0.0,
            "realized_profit": 0.0,
            "fees_total_usd": 5.55,
            "slippage_total_usd": 0.37,
            "arb_type": "perfect",
            "total_cost_per_unit": 79.55,
            "bet_amount_config": 100.0
        },
        {
            "id": "TOT@BRE",
            "game": "Tottenham vs Brentford",
            "sport": "SOCCER",
            "timestamp": "2025-12-03T12:19:23.526368",
            "legs": [
                {
                    "platform": "Kalshi",
                    "price": 43.5,
                    "eff": 46.7625,
                    "team": "Tottenham",
                    "code": "TOT",
                    "market_id": null,
                    "url": "https://kalshi.com/markets/KXEPLGAME-25DEC06TOTBRE-TOT",
                    "fee_rate": 0.07,
                    "cost_usd": 46.7625,
                    "fee_usd": 3.2625,
                    "payout_usd": 100.0,
                    "slippage_usd": 0.2175
                },
                {
                    "platform": "Kalshi",
                    "price": 30.5,
                    "eff": 32.7875,
                    "team": "Brentford",
                    "code": "BRE",
                    "market_id": null,
                    "url": "https://kalshi.com/markets/KXEPLGAME-25DEC06TOTBRE-TOT",
                    "fee_rate": 0.07,
                    "cost_usd": 32.7875,
                    "fee_usd": 2.2875,
                    "payout_usd": 100.0,
                    "slippage_usd": 0.1525
                }
            ],
            "quantity": 100.0,
            "cost": 79.55,
            "payout": 100.0,
            "profit": 20.45,
            "roi_percent": 25.7071,
            "status": "pending",
            "settled_amount": 0.0,
            "realized_profit": 0.0,
            "fees_total_usd": 5.550000000000001,
            "slippage_total_usd": 0.37,
            "arb_type": "perfect",
            "total_cost_per_unit": 79.55,
            "bet_amount_config": 100.0
        },
        {
            "id": "BHA@AVL",
            "game": "Brighton vs Aston Villa",
            "sport": "SOCCER",
            "timestamp": "2025-12-03T12:19:23.528538",
            "legs": [
                {
                    "platform": "Kalshi",
                    "price": 46.0,
                    "eff": 49.45,
                    "team": "Brighton",
                    "code": "BHA",
                    "market_id": null,
                    "url": "https://kalshi.com/markets/KXEPLGAME-25DEC03BRIAVL-TIE",
                    "fee_rate": 0.07,
                    "cost_usd": 49.45,
                    "fee_usd": 3.45,
                    "payout_usd": 100.0,
                    "slippage_usd": 0.23
                },
                {
                    "platform": "Kalshi",
                    "price": 28.5,
                    "eff": 30.6375,
                    "team": "Aston Villa",
                    "code": "AVL",
                    "market_id": null,
                    "url": "https://kalshi.com/markets/KXEPLGAME-25DEC03BRIAVL-TIE",
                    "fee_rate": 0.07,
                    "cost_usd": 30.6375,
                    "fee_usd": 2.1375,
                    "payout_usd": 100.0,
                    "slippage_usd": 0.14250000000000002
                }
            ],
            "quantity": 100.0,
            "cost": 80.0875,
            "payout": 100.0,
            "profit": 19.9125,
            "roi_percent": 24.8634,
            "status": "pending",
            "settled_amount": 0.0,
            "realized_profit": 0.0,
            "fees_total_usd": 5.5875,
            "slippage_total_usd": 0.37250000000000005,
            "arb_type": "perfect",
            "total_cost_per_unit": 80.0875,
            "bet_amount_config": 100.0
        },
        {
            "id": "BUR@FUL",
            "game": "Burnley vs Fulham",
            "sport": "SOCCER",
            "timestamp": "2025-12-03T12:19:23.531264",
            "legs": [
                {
                    "platform": "Polymarket",
                    "price": 34.0,
                    "eff": 34.85,
                    "team": "Burnley",
                    "code": "BUR",
                    "market_id": "768253",
                    "url": "https://polymarket.com/event/epl-bur-ful-2025-12-13",
                    "fee_rate": 0.02,
                    "cost_usd": 34.85,
                    "fee_usd": 0.85,
                    "payout_usd": 100.0,
                    "slippage_usd": 0.17
                },
                {
                    "platform": "Kalshi",
                    "price": 43.0,
                    "eff": 46.225,
                    "team": "Fulham",
                    "code": "FUL",
                    "market_id": null,
                    "url": "https://kalshi.com/markets/KXEPLGAME-25DEC13BURFUL-TIE",
                    "fee_rate": 0.07,
                    "cost_usd": 46.225,
                    "fee_usd": 3.225,
                    "payout_usd": 100.0,
                    "slippage_usd": 0.215
                }
            ],
            "quantity": 100.0,
            "cost": 81.075,
            "payout": 100.0,
            "profit": 18.925,
            "roi_percent": 23.3426,
            "status": "pending",
            "settled_amount": 0.0,
            "realized_profit": 0.0,
            "fees_total_usd": 4.075,
            "slippage_total_usd": 0.385,
            "arb_type": "perfect",
            "total_cost_per_unit": 81.075,
            "bet_amount_config": 100.0
        },
        {
            "id": "BUR@CRY",
            "game": "Burnley vs Crystal Palace",
            "sport": "SOCCER",
            "timestamp": "2025-12-03T12:19:23.533535",
            "legs": [
                {
                    "platform": "Kalshi",
                    "price": 19.5,
                    "eff": 20.9625,
                    "team": "Burnley",
                    "code": "BUR",
                    "market_id": null,
                    "url": "https://kalshi.com/markets/KXEPLGAME-25DEC03BURCRY-TIE",
                    "fee_rate": 0.07,
                    "cost_usd": 20.9625,
                    "fee_usd": 1.4625,
                    "payout_usd": 100.0,
                    "slippage_usd": 0.0975
                },
                {
                    "platform": "Kalshi",
                    "price": 56.0,
                    "eff": 60.2,
                    "team": "Crystal Palace",
                    "code": "CRY",
                    "market_id": null,
                    "url": "https://kalshi.com/markets/KXEPLGAME-25DEC03BURCRY-TIE",
                    "fee_rate": 0.07,
                    "cost_usd": 60.2,
                    "fee_usd": 4.2,
                    "payout_usd": 100.0,
                    "slippage_usd": 0.28
                }
            ],
            "quantity": 100.0,
            "cost": 81.1625,
            "payout": 100.0,
            "profit": 18.8375,
            "roi_percent": 23.2096,
            "status": "pending",
            "settled_amount": 0.0,
            "realized_profit": 0.0,
            "fees_total_usd": 5.6625,
            "slippage_total_usd": 0.37750000000000006,
            "arb_type": "perfect",
            "total_cost_per_unit": 81.1625,
            "bet_amount_config": 100.0
        },
        {
            "id": "BOU@CHE",
            "game": "Bournemouth vs Chelsea",
            "sport": "SOCCER",
            "timestamp": "2025-12-03T12:19:23.535370",
            "legs": [
                {
                    "platform": "Kalshi",
                    "price": 30.0,
                    "eff": 32.25,
                    "team": "Bournemouth",
                    "code": "BOU",
                    "market_id": null,
                    "url": "https://kalshi.com/markets/KXEPLGAME-25DEC06BOUCFC-TIE",
                    "fee_rate": 0.07,
                    "cost_usd": 32.25,
                    "fee_usd": 2.25,
                    "payout_usd": 100.0,
                    "slippage_usd": 0.15
                },
                {
                    "platform": "Kalshi",
                    "price": 46.0,
                    "eff": 49.45,
                    "team": "Chelsea",
                    "code": "CHE",
                    "market_id": null,
                    "url": "https://kalshi.com/markets/KXEPLGAME-25DEC06BOUCFC-TIE",
                    "fee_rate": 0.07,
                    "cost_usd": 49.45,
                    "fee_usd": 3.45,
                    "payout_usd": 100.0,
                    "slippage_usd": 0.23
                }
            ],
            "quantity": 100.0,
            "cost": 81.7,
            "payout": 100.0,
            "profit": 18.3,
            "roi_percent": 22.399,
            "status": "pending",
            "settled_amount": 0.0,
            "realized_profit": 0.0,
            "fees_total_usd": 5.7,
            "slippage_total_usd": 0.38,
            "arb_type": "perfect",
            "total_cost_per_unit": 81.7,
            "bet_amount_config": 100.0
        },
        {
            "id": "BHA@WHU",
            "game": "Brighton vs West Ham",
            "sport": "SOCCER",
            "timestamp": "2025-12-03T12:19:23.537539",
            "legs": [
                {
                    "platform": "Kalshi",
                    "price": 61.0,
                    "eff": 65.575,
                    "team": "Brighton",
                    "code": "BHA",
                    "market_id": null,
                    "url": "https://kalshi.com/markets/KXEPLGAME-25DEC07BRIWHU-WHU",
                    "fee_rate": 0.07,
                    "cost_usd": 65.575,
                    "fee_usd": 4.575,
                    "payout_usd": 100.0,
                    "slippage_usd": 0.305
                },
                {
                    "platform": "Kalshi",
                    "price": 17.5,
                    "eff": 18.8125,
                    "team": "West Ham",
                    "code": "WHU",
                    "market_id": null,
                    "url": "https://kalshi.com/markets/KXEPLGAME-25DEC07BRIWHU-WHU",
                    "fee_rate": 0.07,
                    "cost_usd": 18.8125,
                    "fee_usd": 1.3125,
                    "payout_usd": 100.0,
                    "slippage_usd": 0.0875
                }
            ],
            "quantity": 100.0,
            "cost": 84.3875,
            "payout": 100.0,
            "profit": 15.6125,
            "roi_percent": 18.501,
            "status": "pending",
            "settled_amount": 0.0,
            "realized_profit": 0.0,
            "fees_total_usd": 5.8875,
            "slippage_total_usd": 0.39249999999999996,
            "arb_type": "perfect",
            "total_cost_per_unit": 84.3875,
            "bet_amount_config": 100.0
        },
        {
            "id": "LIV@BHA",
            "game": "Liverpool vs Brighton & Hove Albion",
            "sport": "SOCCER",
            "timestamp": "2025-12-03T12:19:23.539646",
            "legs": [
                {
                    "platform": "Kalshi",
                    "price": 43.0,
                    "eff": 46.225,
                    "team": "Liverpool",
                    "code": "LIV",
                    "market_id": null,
                    "url": "https://kalshi.com/markets/KXEPLGAME-25DEC13LFCBRI-TIE",
                    "fee_rate": 0.07,
                    "cost_usd": 46.225,
                    "fee_usd": 3.225,
                    "payout_usd": 100.0,
                    "slippage_usd": 0.215
                },
                {
                    "platform": "Polymarket",
                    "price": 40.0,
                    "eff": 41.0,
                    "team": "Brighton & Hove Albion",
                    "code": "BHA",
                    "market_id": "768225",
                    "url": "https://polymarket.com/event/epl-liv-bri-2025-12-13",
                    "fee_rate": 0.02,
                    "cost_usd": 41.0,
                    "fee_usd": 1.0,
                    "payout_usd": 100.0,
                    "slippage_usd": 0.2
                }
            ],
            "quantity": 100.0,
            "cost": 87.225,
            "payout": 100.0,
            "profit": 12.775,
            "roi_percent": 14.646,
            "status": "pending",
            "settled_amount": 0.0,
            "realized_profit": 0.0,
            "fees_total_usd": 4.225,
            "slippage_total_usd": 0.41500000000000004,
            "arb_type": "perfect",
            "total_cost_per_unit": 87.225,
            "bet_amount_config": 100.0
        },
        {
            "id": "SEA@EDM",
            "game": "Kraken vs Oilers",
            "sport": "NHL",
            "timestamp": "2025-12-03T12:19:23.541438",
            "legs": [
                {
                    "platform": "Kalshi",
                    "price": 34.0,
                    "eff": 36.55,
                    "team": "Kraken",
                    "code": "SEA",
                    "market_id": null,
                    "url": "https://kalshi.com/markets/KXNHLGAME-25DEC04SEAEDM-SEA",
                    "fee_rate": 0.07,
                    "cost_usd": 36.55,
                    "fee_usd": 2.5499999999999954,
                    "payout_usd": 100.0,
                    "slippage_usd": 0.17
                },
                {
                    "platform": "Kalshi",
                    "price": 48.0,
                    "eff": 51.6,
                    "team": "Oilers",
                    "code": "EDM",
                    "market_id": null,
                    "url": "https://kalshi.com/markets/KXNHLGAME-25DEC04SEAEDM-SEA",
                    "fee_rate": 0.07,
                    "cost_usd": 51.6,
                    "fee_usd": 3.6,
                    "payout_usd": 100.0,
                    "slippage_usd": 0.24
                }
            ],
            "quantity": 100.0,
            "cost": 88.15,
            "payout": 100.0,
            "profit": 11.85,
            "roi_percent": 13.443,
            "status": "pending",
            "settled_amount": 0.0,
            "realized_profit": 0.0,
            "fees_total_usd": 6.149999999999995,
            "slippage_total_usd": 0.41000000000000003,
            "arb_type": "perfect",
            "total_cost_per_unit": 88.15,
            "bet_amount_config": 100.0
        },
        {
            "id": "ARS@BRE",
            "game": "Arsenal vs Brentford",
            "sport": "SOCCER",
            "timestamp": "2025-12-03T12:19:23.543055",
            "legs": [
                {
                    "platform": "Kalshi",
                    "price": 70.5,
                    "eff": 75.7875,
                    "team": "Arsenal",
                    "code": "ARS",
                    "market_id": null,
                    "url": "https://kalshi.com/markets/KXEPLGAME-25DEC03ARSBRE-TIE",
                    "fee_rate": 0.07,
                    "cost_usd": 75.7875,
                    "fee_usd": 5.287499999999991,
                    "payout_usd": 100.0,
                    "slippage_usd": 0.3525
                },
                {
                    "platform": "Kalshi",
                    "price": 11.5,
                    "eff": 12.3625,
                    "team": "Brentford",
                    "code": "BRE",
                    "market_id": null,
                    "url": "https://kalshi.com/markets/KXEPLGAME-25DEC03ARSBRE-TIE",
                    "fee_rate": 0.07,
                    "cost_usd": 12.3625,
                    "fee_usd": 0.8625,
                    "payout_usd": 100.0,
                    "slippage_usd": 0.0575
                }
            ],
            "quantity": 100.0,
            "cost": 88.15,
            "payout": 100.0,
            "profit": 11.85,
            "roi_percent": 13.443,
            "status": "pending",
            "settled_amount": 0.0,
            "realized_profit": 0.0,
            "fees_total_usd": 6.149999999999991,
            "slippage_total_usd": 0.41,
            "arb_type": "perfect",
            "total_cost_per_unit": 88.15,
            "bet_amount_config": 100.0
        },
        {
            "id": "LIV@SUN",
            "game": "Liverpool vs Sunderland",
            "sport": "SOCCER",
            "timestamp": "2025-12-03T12:19:23.545111",
            "legs": [
                {
                    "platform": "Kalshi",
                    "price": 71.0,
                    "eff": 76.325,
                    "team": "Liverpool",
                    "code": "LIV",
                    "market_id": null,
                    "url": "https://kalshi.com/markets/KXEPLGAME-25DEC03LFCSUN-TIE",
                    "fee_rate": 0.07,
                    "cost_usd": 76.325,
                    "fee_usd": 5.325,
                    "payout_usd": 100.0,
                    "slippage_usd": 0.355
                },
                {
                    "platform": "Polymarket",
                    "price": 13.0,
                    "eff": 13.325,
                    "team": "Sunderland",
                    "code": "SUN",
                    "market_id": "692732",
                    "url": "https://polymarket.com/event/epl-liv-sun-2025-12-03",
                    "fee_rate": 0.02,
                    "cost_usd": 13.325,
                    "fee_usd": 0.325,
                    "payout_usd": 100.0,
                    "slippage_usd": 0.065
                }
            ],
            "quantity": 100.0,
            "cost": 89.65,
            "payout": 100.0,
            "profit": 10.35,
            "roi_percent": 11.5449,
            "status": "pending",
            "settled_amount": 0.0,
            "realized_profit": 0.0,
            "fees_total_usd": 5.65,
            "slippage_total_usd": 0.42,
            "arb_type": "perfect",
            "total_cost_per_unit": 89.65,
            "bet_amount_config": 100.0
        },
        {
            "id": "NEW@BUR",
            "game": "Newcastle vs Burnley",
            "sport": "SOCCER",
            "timestamp": "2025-12-03T12:19:23.546930",
            "legs": [
                {
                    "platform": "Kalshi",
                    "price": 76.5,
                    "eff": 82.2375,
                    "team": "Newcastle",
                    "code": "NEW",
                    "market_id": null,
                    "url": "https://kalshi.com/markets/KXEPLGAME-25DEC06NEWBUR-TIE",
                    "fee_rate": 0.07,
                    "cost_usd": 82.2375,
                    "fee_usd": 5.7375,
                    "payout_usd": 100.0,
                    "slippage_usd": 0.3825
                },
                {
                    "platform": "Kalshi",
                    "price": 9.0,
                    "eff": 9.675,
                    "team": "Burnley",
                    "code": "BUR",
                    "market_id": null,
                    "url": "https://kalshi.com/markets/KXEPLGAME-25DEC06NEWBUR-TIE",
                    "fee_rate": 0.07,
                    "cost_usd": 9.675,
                    "fee_usd": 0.6750000000000012,
                    "payout_usd": 100.0,
                    "slippage_usd": 0.045
                }
            ],
            "quantity": 100.0,
            "cost": 91.9125,
            "payout": 100.0,
            "profit": 8.0875,
            "roi_percent": 8.7991,
            "status": "pending",
            "settled_amount": 0.0,
            "realized_profit": 0.0,
            "fees_total_usd": 6.412500000000001,
            "slippage_total_usd": 0.4275,
            "arb_type": "perfect",
            "total_cost_per_unit": 91.9125,
            "bet_amount_config": 100.0
        },
        {
            "id": "WHU@AVL",
            "game": "West Ham United vs Aston Villa",
            "sport": "SOCCER",
            "timestamp": "2025-12-03T12:19:23.549125",
            "legs": [
                {
                    "platform": "Kalshi",
                    "price": 43.0,
                    "eff": 46.225,
                    "team": "West Ham United",
                    "code": "WHU",
                    "market_id": null,
                    "url": "https://kalshi.com/markets/KXEPLGAME-25DEC14WHUAVL-WHU",
                    "fee_rate": 0.07,
                    "cost_usd": 46.225,
                    "fee_usd": 3.225,
                    "payout_usd": 100.0,
                    "slippage_usd": 0.215
                },
                {
                    "platform": "Kalshi",
                    "price": 43.0,
                    "eff": 46.225,
                    "team": "Aston Villa",
                    "code": "AVL",
                    "market_id": null,
                    "url": "https://kalshi.com/markets/KXEPLGAME-25DEC14WHUAVL-WHU",
                    "fee_rate": 0.07,
                    "cost_usd": 46.225,
                    "fee_usd": 3.225,
                    "payout_usd": 100.0,
                    "slippage_usd": 0.215
                }
            ],
            "quantity": 100.0,
            "cost": 92.45,
            "payout": 100.0,
            "profit": 7.55,
            "roi_percent": 8.1666,
            "status": "pending",
            "settled_amount": 0.0,
            "realized_profit": 0.0,
            "fees_total_usd": 6.45,
            "slippage_total_usd": 0.43,
            "arb_type": "perfect",
            "total_cost_per_unit": 92.45,
            "bet_amount_config": 100.0
        },
        {
            "id": "TEST1@TEST2",
            "game": "Test Team 1 vs Test Team 2",
            "sport": "test",
            "timestamp": "2025-12-03T12:22:07.628448",
            "legs": [
                {
                    "platform": "Polymarket",
                    "price": 40,
                    "eff": 40.8,
                    "team": "Test Team 1",
                    "code": "TEST1",
                    "market_id": "test123",
                    "url": "",
                    "fee_rate": 0.02,
                    "cost_usd": 40.8,
                    "fee_usd": 0.7999999999999955,
                    "payout_usd": 100.0,
                    "slippage_usd": 0.2
                },
                {
                    "platform": "Kalshi",
                    "price": 45,
                    "eff": 45.9,
                    "team": "Test Team 2",
                    "code": "TEST2",
                    "market_id": null,
                    "url": "",
                    "fee_rate": 0.07,
                    "cost_usd": 45.9,
                    "fee_usd": 0.9,
                    "payout_usd": 100.0,
                    "slippage_usd": 0.225
                }
            ],
            "quantity": 100.0,
            "cost": 86.7,
            "payout": 100.0,
            "profit": 13.3,
            "roi_percent": 15.34,
            "status": "pending",
            "settled_amount": 0.0,
            "realized_profit": 0.0,
            "fees_total_usd": 1.6999999999999955,
            "slippage_total_usd": 0.42500000000000004,
            "arb_type": "perfect",
            "total_cost_per_unit": 86.7,
            "bet_amount_config": 100.0
        }
    ],
    "total_profit": 0.0
}